cli.py
beacon_datalake_cli-0.1.0.dist-info/licenses/LICENSE
beacon_datalake_cli-0.1.0.dist-info/METADATA
beacon_datalake_cli-0.1.0.dist-info/WHEEL
beacon_datalake_cli-0.1.0.dist-info/entry_points.txt
beacon_datalake_cli-0.1.0.dist-info/top_level.txt
beacon_datalake_cli-0.1.0.dist-info/RECORD
