Metadata-Version: 2.4
Name: beacon-datalake-cli
Version: 0.1.0
Summary: Command-line interface for Beacon Data Lake nodes
Author: Beacon Data Lake
License:                     GNU AFFERO GENERAL PUBLIC LICENSE
Keywords: beacon,datalake,cli
Classifier: Development Status :: 3 - Alpha
Classifier: Intended Audience :: Developers
Classifier: License :: OSI Approved :: GNU Affero General Public License v3
Classifier: Programming Language :: Python
Classifier: Programming Language :: Python :: 3
Classifier: Programming Language :: Python :: 3.10
Classifier: Programming Language :: Python :: 3.11
Classifier: Programming Language :: Python :: 3.12
Classifier: Programming Language :: Python :: 3.13
Classifier: Operating System :: OS Independent
Classifier: Topic :: Utilities
Requires-Python: >=3.10
License-File: LICENSE
Requires-Dist: beacon-api>=1.1.3
Requires-Dist: cmd2>=2.4
Requires-Dist: pandas>=2.0
Requires-Dist: pyarrow>=14.0
Requires-Dist: rich>=13.0
Dynamic: license-file
